pyrena/__init__.py
pyrena/classes/__init__.py
pyrena/classes/base.py
pyrena/classes/bom.py
pyrena/classes/change.py
pyrena/classes/eventqueue.py
pyrena/classes/extract.py
pyrena/classes/file.py
pyrena/classes/item.py
pyrena/classes/quality.py
pyrena/classes/supplier.py
pyrena/classes/tickets.py
pyrena/classes/training.py
pyrena/classes/user.py
pyrena-1.4.3.dist-info/licenses/LICENSE.txt
pyrena-1.4.3.dist-info/METADATA
pyrena-1.4.3.dist-info/WHEEL
pyrena-1.4.3.dist-info/top_level.txt
pyrena-1.4.3.dist-info/RECORD
