Metadata-Version: 2.4
Name: pyrena
Version: 1.4.3
Summary: Python wrapper for Arena QMS API.
Home-page: https://github.com/thecodeforge/pyrena
Requires-Python: >=3.7
License-File: LICENSE.txt
Requires-Dist: mistletoe
Requires-Dist: requests
Dynamic: description
Dynamic: description-content-type
Dynamic: home-page
Dynamic: license-file
Dynamic: requires-dist
Dynamic: requires-python
Dynamic: summary
